applipy_inject/__init__.py
applipy_inject/inject.py
applipy_inject/py.typed
applipy_inject/version.py
applipy_inject-1.4.1.dist-info/LICENSE
applipy_inject-1.4.1.dist-info/METADATA
applipy_inject-1.4.1.dist-info/WHEEL
applipy_inject-1.4.1.dist-info/top_level.txt
applipy_inject-1.4.1.dist-info/RECORD
