Metadata-Version: 2.1
Name: applipy-inject
Version: 1.4.1
Summary: Library that provides a dependency injector that works with type hinting.
Home-page: https://gitlab.com/applipy/applipy_inject
Author: Alessio Linares
Author-email: mail@alessio.cc
License: Apache 2.0
Project-URL: Source, https://gitlab.com/applipy/applipy_inject
Classifier: Development Status :: 5 - Production/Stable
Classifier: Intended Audience :: Developers
Classifier: License :: OSI Approved :: Apache Software License
Classifier: Programming Language :: Python :: 3.9
Classifier: Topic :: Software Development :: Libraries
Requires-Python: >=3.10
License-File: LICENSE
